odoo10_addon_hr_contract_reference-10.0.1.0.0-py2.7-nspkg.pth
odoo10_addon_hr_contract_reference-10.0.1.0.0.dist-info/top_level.txt
odoo10_addon_hr_contract_reference-10.0.1.0.0.dist-info/WHEEL
odoo10_addon_hr_contract_reference-10.0.1.0.0.dist-info/RECORD
odoo10_addon_hr_contract_reference-10.0.1.0.0.dist-info/metadata.json
odoo10_addon_hr_contract_reference-10.0.1.0.0.dist-info/DESCRIPTION.rst
odoo10_addon_hr_contract_reference-10.0.1.0.0.dist-info/METADATA
odoo10_addon_hr_contract_reference-10.0.1.0.0.dist-info/namespace_packages.txt
odoo/addons/hr_contract_reference/__manifest__.py
odoo/addons/hr_contract_reference/__init__.py
odoo/addons/hr_contract_reference/README.rst
odoo/addons/hr_contract_reference/models/hr_contract.py
odoo/addons/hr_contract_reference/models/__init__.py
odoo/addons/hr_contract_reference/i18n/it.po
odoo/addons/hr_contract_reference/i18n/es.po
odoo/addons/hr_contract_reference/i18n/ro.po
odoo/addons/hr_contract_reference/i18n/sl.po
odoo/addons/hr_contract_reference/i18n/de.po
odoo/addons/hr_contract_reference/i18n/fr.po
odoo/addons/hr_contract_reference/i18n/pt_BR.po
odoo/addons/hr_contract_reference/i18n/fi.po
odoo/addons/hr_contract_reference/views/hr_contract_view.xml
odoo/addons/hr_contract_reference/data/hr_contract_sequence.xml
odoo/addons/hr_contract_reference/static/description/icon.png
